{
  "legend": {
    "#000001": "mountain",
    "#000005": "static",
    "#001433": "ego_vehicle",
    "#06cb56": "Car # 10",
    "#141414": "rectification_border",
    "#19eda6": "Car # 21",
    "#1d5073": "Car # 11",
    "#1fb1c2": "Truck # 1",
    "#21964f": "Car # 22",
    "#220760": "Car # 16",
    "#2a0ed4": "Motorcycle",
    "#3224ea": "Car # 2",
    "#3b0722": "Car # 23",
    "#3d9700": "Car # 12",
    "#464646": "building",
    "#4682b4": "sky",
    "#510051": "ground",
    "#511616": "cycle",
    "#51a943": "Person",
    "#53de46": "person_group",
    "#550055": "licenseplate",
    "#5cf414": "Car # 4",
    "#5f90c4": "Truck",
    "#66669c": "wall",
    "#6b8e23": "vegetation",
    "#6f4a00": "dynamic",
    "#729ae6": "Car # 17",
    "#804080": "road",
    "#8eee74": "Car # 20",
    "#966464": "bridge",
    "#96785a": "tunnel",
    "#98fb98": "terrain",
    "#999999": "pole",
    "#a051c8": "Car # 24",
    "#a770af": "Car # 18",
    "#aad3c6": "Car # 13",
    "#ae4043": "billboard",
    "#aed088": "Car # 9",
    "#b064aa": "Caravan # 1",
    "#b4a5b4": "guardrail",
    "#b5f23f": "Car # 7",
    "#bcef80": "Car # 19",
    "#be9999": "fence",
    "#c00080": "tram track",
    "#c1b3b3": "Car",
    "#c45a40": "Car # 1",
    "#c8e7d7": "Car # 3",
    "#cac271": "Bus",
    "#cd6dc4": "Bus # 1",
    "#cfb03e": "car_group",
    "#d2aa64": "street light",
    "#dc4c78": "Caravan",
    "#dc5b12": "Car # 15",
    "#dcdc00": "traffic_sign",
    "#df7348": "Train",
    "#e6968c": "rail track",
    "#e7f259": "Car # 6",
    "#e972cc": "Trailer",
    "#f10819": "Car # 5",
    "#f29449": "Truck # 2",
    "#f423e8": "sidewalk",
    "#f423f2": "cycle_group",
    "#f5c89c": "Car # 14",
    "#f9f131": "Car # 8",
    "#faaa1e": "traffic_light",
    "#faaaa0": "parking",
    "#ff0000": "rider",
    "#ffffff": "unlabeled"
  }
}